aws_mlops/__init__.py
aws_mlops/automl.py
aws_mlops/config_manager.py
aws_mlops/data_storage.py
aws_mlops/get_best_job.py
aws_mlops/mlops.py
tests/__init__.py
tests/config.py
tests/definitions.py
tests/test_config_manager.py
tests/test_data_storage.py
tests/test_get_best_job.py
tests/test_mlops.py
aws_mlops-1.2.2.dist-info/LICENSE
aws_mlops-1.2.2.dist-info/METADATA
aws_mlops-1.2.2.dist-info/WHEEL
aws_mlops-1.2.2.dist-info/top_level.txt
aws_mlops-1.2.2.dist-info/RECORD
