Metadata-Version: 2.1
Name: aws-mlops
Version: 1.2.2
Summary: AWS MLOps Python package
Home-page: https://aws-mlops.readthedocs.io/
Author: Alessandra Bilardi
Author-email: alessandra.bilardi@gmail.com
License: UNKNOWN
Project-URL: Source, https://github.com/bilardi/aws-mlops
Project-URL: Bug Reports, https://github.com/bilardi/aws-mlops/issues
Project-URL: Funding, https://donate.pypi.org
Platform: UNKNOWN
Classifier: Programming Language :: Python :: 3
Classifier: License :: OSI Approved :: MIT License
Classifier: Operating System :: OS Independent
Requires-Python: >=3.6
License-File: LICENSE
